setup.cfg
setup.py
mr_logger/__init__.py
mr_logger/logger.py
mr_logger.egg-info/PKG-INFO
mr_logger.egg-info/SOURCES.txt
mr_logger.egg-info/dependency_links.txt
mr_logger.egg-info/requires.txt
mr_logger.egg-info/top_level.txt