Metadata-Version: 1.1
Name: mr-logger
Version: 0.1
Summary: Small colored logger
Home-page: https://github.com/r00tkid/mr_logger.git
Author: Root Kid
Author-email: shaman@born2fish.ru
License: UNKNOWN
Download-URL: https://github.com/r00tkid/mr_logger/tarball/0.1
Keywords: support,logging,webdev
Platform: UNKNOWN
